{
  "fingerprint_id": "987654321",
  "minutiae_points": [
    {"x": 149, "y": 201, "type": "ridge_ending", "orientation": 46},
    {"x": 161, "y": 211, "type": "bifurcation", "orientation": 59},
    {"x": 169, "y": 221, "type": "ridge_ending", "orientation": 31},
    {"x": 181, "y": 231, "type": "bifurcation", "orientation": 89},
    {"x": 191, "y": 239, "type": "ridge_ending", "orientation": 44},
    {"x": 199, "y": 251, "type": "bifurcation", "orientation": 121},
    {"x": 211, "y": 261, "type": "ridge_ending", "orientation": 76},
    {"x": 221, "y": 271, "type": "bifurcation", "orientation": 134},
    {"x": 229, "y": 281, "type": "ridge_ending", "orientation": 61},
    {"x": 241, "y": 289, "type": "bifurcation", "orientation": 149},
    {"x": 251, "y": 301, "type": "ridge_ending", "orientation": 32},
    {"x": 259, "y": 311, "type": "bifurcation", "orientation": 46},
    {"x": 271, "y": 319, "type": "ridge_ending", "orientation": 91},
    {"x": 279, "y": 331, "type": "bifurcation", "orientation": 59},
    {"x": 291, "y": 341, "type": "ridge_ending", "orientation": 121},
    {"x": 299, "y": 351, "type": "bifurcation", "orientation": 136},
    {"x": 311, "y": 359, "type": "ridge_ending", "orientation": 74},
    {"x": 319, "y": 371, "type": "bifurcation", "orientation": 44},
    {"x": 331, "y": 379, "type": "ridge_ending", "orientation": 151},
    {"x": 341, "y": 391, "type": "bifurcation", "orientation": 31},
    {"x": 349, "y": 401, "type": "ridge_ending", "orientation": 89},
    {"x": 361, "y": 409, "type": "bifurcation", "orientation": 121},
    {"x": 371, "y": 421, "type": "ridge_ending", "orientation": 59},
    {"x": 381, "y": 431, "type": "bifurcation", "orientation": 46},
    {"x": 391, "y": 441, "type": "ridge_ending", "orientation": 149},
    {"x": 401, "y": 451, "type": "bifurcation", "orientation": 76},
    {"x": 411, "y": 459, "type": "ridge_ending", "orientation": 134},
    {"x": 421, "y": 471, "type": "bifurcation", "orientation": 91},
    {"x": 431, "y": 479, "type": "ridge_ending", "orientation": 121},
    {"x": 439, "y": 491, "type": "bifurcation", "orientation": 59}
  ]
}